pymana/__init__.py
pymana/cli.py
pymana/correction.py
pymana/detection.py
pymana/separation.py
pymana/utils.py
pymana-0.1.6.dist-info/entry_points.txt
pymana-0.1.6.dist-info/LICENSE
pymana-0.1.6.dist-info/WHEEL
pymana-0.1.6.dist-info/METADATA
pymana-0.1.6.dist-info/RECORD
